djopenapi/__init__.py
djopenapi/api_client.py
djopenapi/apis/__init__.py
djopenapi/apis/path_to_api.py
djopenapi/apis/paths/__init__.py
djopenapi/apis/paths/attributes_.py
djopenapi/apis/paths/catalogs_.py
djopenapi/apis/paths/catalogs_name_.py
djopenapi/apis/paths/catalogs_name_engines_.py
djopenapi/apis/paths/cubes_name_.py
djopenapi/apis/paths/data_node_name_.py
djopenapi/apis/paths/data_node_name_availability_.py
djopenapi/apis/paths/engines_.py
djopenapi/apis/paths/engines_name_version_.py
djopenapi/apis/paths/health_.py
djopenapi/apis/paths/metrics_.py
djopenapi/apis/paths/metrics_common_dimensions_.py
djopenapi/apis/paths/metrics_name_.py
djopenapi/apis/paths/nodes_.py
djopenapi/apis/paths/nodes_cube_.py
djopenapi/apis/paths/nodes_dimension_.py
djopenapi/apis/paths/nodes_metric_.py
djopenapi/apis/paths/nodes_name_.py
djopenapi/apis/paths/nodes_name_columns_column_.py
djopenapi/apis/paths/nodes_name_downstream_.py
djopenapi/apis/paths/nodes_name_materialization_.py
djopenapi/apis/paths/nodes_name_revisions_.py
djopenapi/apis/paths/nodes_name_tag_.py
djopenapi/apis/paths/nodes_node_name_attributes_.py
djopenapi/apis/paths/nodes_similarity_node1_name_node2_name.py
djopenapi/apis/paths/nodes_source_.py
djopenapi/apis/paths/nodes_transform_.py
djopenapi/apis/paths/nodes_validate_.py
djopenapi/apis/paths/query_sql.py
djopenapi/apis/paths/sql_node_name_.py
djopenapi/apis/paths/tags_.py
djopenapi/apis/paths/tags_name_.py
djopenapi/apis/paths/tags_name_nodes_.py
djopenapi/apis/tag_to_api.py
djopenapi/apis/tags/__init__.py
djopenapi/apis/tags/default_api.py
djopenapi/configuration.py
djopenapi/exceptions.py
djopenapi/model/__init__.py
djopenapi/model/attribute_output.py
djopenapi/model/attribute_output.pyi
djopenapi/model/attribute_type.py
djopenapi/model/attribute_type.pyi
djopenapi/model/attribute_type_name.py
djopenapi/model/attribute_type_name.pyi
djopenapi/model/availability_state.py
djopenapi/model/availability_state.pyi
djopenapi-0.0.1a1.dist-info/METADATA
djopenapi-0.0.1a1.dist-info/WHEEL
djopenapi-0.0.1a1.dist-info/RECORD
