Metadata-Version: 2.1
Name: djopenapi
Version: 0.0.1a1
Summary: DataJunction client autogenerated from the OpenAPI spec
Home-page: https://github.com/DataJunction/dj
License: MIT
Author: DataJunction Authors
Requires-Python: >=3.8,<4.0
Classifier: License :: OSI Approved :: MIT License
Classifier: Programming Language :: Python :: 3
Classifier: Programming Language :: Python :: 3.8
Classifier: Programming Language :: Python :: 3.9
Classifier: Programming Language :: Python :: 3.10
Classifier: Programming Language :: Python :: 3.11
Requires-Dist: certifi (>=14.5.14)
Requires-Dist: frozendict (>=2.3.4,<2.4.0)
Requires-Dist: python-dateutil (>=2.7.0,<2.8.0)
Requires-Dist: setuptools (>=21.0.0)
Requires-Dist: typing-extensions (>=4.3.0,<4.4.0)
Requires-Dist: urllib3 (>=1.26.7,<1.27.0)
Project-URL: Repository, https://github.com/DataJunction/dj
